pyledlanglib/__init__.py
pyledlanglib-0.1.2.dist-info/LICENSE
pyledlanglib-0.1.2.dist-info/METADATA
pyledlanglib-0.1.2.dist-info/WHEEL
pyledlanglib-0.1.2.dist-info/top_level.txt
pyledlanglib-0.1.2.dist-info/RECORD
