Metadata-Version: 2.1
Name: pyledlanglib
Version: 0.1.2
Summary: PyLEdLang compiler on top of Python3
Home-page: https://github.com/alex5250/PyLEDLang-Compiler
Author: Alex Zaslavskis
Author-email: sahsariga111@gmail.com
License: BSD 2-clause
Classifier: Development Status :: 1 - Planning
Classifier: Intended Audience :: Science/Research
Classifier: License :: OSI Approved :: BSD License
Classifier: Operating System :: POSIX :: Linux
Classifier: Programming Language :: Python :: 2
Classifier: Programming Language :: Python :: 2.7
Classifier: Programming Language :: Python :: 3
Classifier: Programming Language :: Python :: 3.4
Classifier: Programming Language :: Python :: 3.11
License-File: LICENSE
